ndexstringloader/__init__.py
ndexstringloader/exceptions.py
ndexstringloader/ndexloadstring.py
ndexstringloader/ndexupdate.py
ndexstringloader/string_plan.json
ndexstringloader/style.cx
ndexstringloader-1.0.3.data/scripts/ndexloadstring.py
ndexstringloader-1.0.3.dist-info/AUTHORS.rst
ndexstringloader-1.0.3.dist-info/LICENSE
ndexstringloader-1.0.3.dist-info/METADATA
ndexstringloader-1.0.3.dist-info/WHEEL
ndexstringloader-1.0.3.dist-info/top_level.txt
ndexstringloader-1.0.3.dist-info/RECORD
