Metadata-Version: 2.1
Name: ndexstringloader
Version: 1.0.3
Summary: Loads STRING data into NDEx
Home-page: https://github.com/ndexcontent/ndexstringloader
Author: Vladimir Rynkov
Author-email: vrynkov@ucsd.edu
License: BSD license
Keywords: ndexstringloader
Platform: UNKNOWN
Classifier: Development Status :: 2 - Pre-Alpha
Classifier: Intended Audience :: Developers
Classifier: License :: OSI Approved :: BSD License
Classifier: Natural Language :: English
Classifier: Programming Language :: Python :: 3.4
Classifier: Programming Language :: Python :: 3.5
Classifier: Programming Language :: Python :: 3.6
Classifier: Programming Language :: Python :: 3.7
License-File: LICENSE
License-File: AUTHORS.rst
Requires-Dist: ndex2
Requires-Dist: ndexutil
Requires-Dist: networkx
Requires-Dist: scipy
Requires-Dist: py4cytoscape
Requires-Dist: requests
Requires-Dist: pandas
